odoo8_addon_l10n_pe_multifunctions-8.0.1.0.0-py2.7-nspkg.pth
odoo8_addon_l10n_pe_multifunctions-8.0.1.0.0.dist-info/top_level.txt
odoo8_addon_l10n_pe_multifunctions-8.0.1.0.0.dist-info/WHEEL
odoo8_addon_l10n_pe_multifunctions-8.0.1.0.0.dist-info/RECORD
odoo8_addon_l10n_pe_multifunctions-8.0.1.0.0.dist-info/metadata.json
odoo8_addon_l10n_pe_multifunctions-8.0.1.0.0.dist-info/DESCRIPTION.rst
odoo8_addon_l10n_pe_multifunctions-8.0.1.0.0.dist-info/METADATA
odoo8_addon_l10n_pe_multifunctions-8.0.1.0.0.dist-info/namespace_packages.txt
odoo_addons/l10n_pe_multifunctions/__openerp__.py
odoo_addons/l10n_pe_multifunctions/__init__.py
odoo_addons/l10n_pe_multifunctions/README.rst
odoo_addons/l10n_pe_multifunctions/i18n/es.po
odoo_addons/l10n_pe_multifunctions/model/__init__.py
odoo_addons/l10n_pe_multifunctions/model/invoice.py
